LICENSE
README.md
user_tel/__init__.py
user_tel/admin.py
user_tel/apps.py
user_tel/factory.py
user_tel/forms.py
user_tel/migrations/0001_initial.py
user_tel/migrations/0002_alter_user_groups_alter_user_user_permissions.py
user_tel/migrations/__init__.py
user_tel/models.py
django_user_tel-1.0.1.dist-info/LICENSE
django_user_tel-1.0.1.dist-info/METADATA
django_user_tel-1.0.1.dist-info/WHEEL
django_user_tel-1.0.1.dist-info/RECORD
