Metadata-Version: 2.1
Name: django-user-tel
Version: 1.0.1
Summary: Custom, simple Django User model with telephone number as username
Home-page: https://github.com/khasbilegt/django-user-tel
License: MIT
Keywords: django,model,user,telephone,phone number,username,custom
Author: Khasbilegt.TS
Author-email: khasbilegt.ts@gmail.com
Requires-Python: >=3.8,<4.0
Classifier: Environment :: Web Environment
Classifier: Framework :: Django
Classifier: Framework :: Django :: 3.2
Classifier: Framework :: Django :: 4.0
Classifier: Framework :: Django :: 4.2
Classifier: Intended Audience :: Developers
Classifier: License :: OSI Approved :: MIT License
Classifier: Programming Language :: Python
Classifier: Programming Language :: Python :: 3
Classifier: Programming Language :: Python :: 3.8
Classifier: Programming Language :: Python :: 3.9
Classifier: Programming Language :: Python :: 3.10
Classifier: Programming Language :: Python :: 3.11
Classifier: Programming Language :: Python :: 3.10
Classifier: Programming Language :: Python :: 3.11
Classifier: Programming Language :: Python :: 3.8
Classifier: Programming Language :: Python :: 3.9
Classifier: Topic :: Software Development :: Build Tools
Project-URL: Repository, https://github.com/khasbilegt/django-user-tel
